camels_aus/__init__.py
camels_aus/_version.py
camels_aus/conventions.py
camels_aus/read.py
camels_aus/repository.py
camels_aus/transforms.py
camels_aus-0.5.dist-info/LICENSE
camels_aus-0.5.dist-info/METADATA
camels_aus-0.5.dist-info/WHEEL
camels_aus-0.5.dist-info/top_level.txt
camels_aus-0.5.dist-info/RECORD
