Metadata-Version: 2.1
Name: camels-aus
Version: 0.5
Summary: Python package to easily access the CAMELS-AUS dataset
Home-page: https://github.com/csiro-hydroinformatics/camels-aus-py
Author: Jean-Michel Perraud
Author-email: per202@csiro.au
License: UNKNOWN
Project-URL: Bug Reports, https://github.com/csiro-hydroinformatics/camels-aus-py/issues
Project-URL: Source, https://github.com/csiro-hydroinformatics/camels-aus-py
Keywords: earth-sciences hydrology forecast
Platform: UNKNOWN
Classifier: Development Status :: 3 - Alpha
Classifier: Intended Audience :: Science/Research
Classifier: License :: OSI Approved :: MIT License
Classifier: Operating System :: OS Independent
Classifier: Topic :: Scientific/Engineering :: Hydrology
Classifier: Topic :: Database
Classifier: Programming Language :: Python
Classifier: Programming Language :: Python :: 3.8
Classifier: Programming Language :: Python :: 3.9
License-File: LICENSE
Requires-Dist: pandas
Requires-Dist: numpy
Requires-Dist: scipy
Requires-Dist: geopandas
Requires-Dist: xarray
